[
    {
        "key": "dbln",
        "value": "%7B%22100089106360219%22%3A%22vF3To3Ah%22%7D",
        "domain": "facebook.com",
        "path": "/login/device-based/",
        "hostOnly": false,
        "creation": "2025-05-15T16:44:54.128Z",
        "lastAccessed": "2025-05-15T16:44:54.129Z"
    },
    {
        "key": "datr",
        "value": "kQ4maHjvXjc-dPqqFxRnYseb",
        "domain": "facebook.com",
        "path": "/",
        "hostOnly": false,
        "creation": "2025-05-15T16:44:54.129Z",
        "lastAccessed": "2025-05-15T16:44:54.129Z"
    },
    {
        "key": "sb",
        "value": "kQ4maPCtYpgn1lwuHM1Kzz-W",
        "domain": "facebook.com",
        "path": "/",
        "hostOnly": false,
        "creation": "2025-05-15T16:44:54.129Z",
        "lastAccessed": "2025-05-15T16:44:54.129Z"
    },
    {
        "key": "c_user",
        "value": "100089106360219",
        "domain": "facebook.com",
        "path": "/",
        "hostOnly": false,
        "creation": "2025-05-15T16:44:54.129Z",
        "lastAccessed": "2025-05-15T16:44:54.129Z"
    },
    {
        "key": "fr",
        "value": "0QXPsE1CN1bwICTg8.AWfaCnTC3J_nf40LWhNH117hWcwuSbay-nAZdM3pUA5qY3wjb9M.BoJg6R..AAA.0.0.BoJg_2.AWdqFB2Kfyyttm0aEFc4WDwC5Lk",
        "domain": "facebook.com",
        "path": "/",
        "hostOnly": false,
        "creation": "2025-05-15T16:44:54.129Z",
        "lastAccessed": "2025-05-15T16:44:54.129Z"
    },
    {
        "key": "xs",
        "value": "20%3AJr1CK1NtkhNpiA%3A2%3A1747324922%3A-1%3A5122",
        "domain": "facebook.com",
        "path": "/",
        "hostOnly": false,
        "creation": "2025-05-15T16:44:54.129Z",
        "lastAccessed": "2025-05-15T16:44:54.129Z"
    },
    {
        "key": "locale",
        "value": "en_GB",
        "domain": "facebook.com",
        "path": "/",
        "hostOnly": false,
        "creation": "2025-05-15T16:44:54.129Z",
        "lastAccessed": "2025-05-15T16:44:54.129Z"
    },
    {
        "key": "ps_l",
        "value": "1",
        "domain": "facebook.com",
        "path": "/",
        "hostOnly": false,
        "creation": "2025-05-15T16:44:54.129Z",
        "lastAccessed": "2025-05-15T16:44:54.129Z"
    },
    {
        "key": "ps_n",
        "value": "1",
        "domain": "facebook.com",
        "path": "/",
        "hostOnly": false,
        "creation": "2025-05-15T16:44:54.130Z",
        "lastAccessed": "2025-05-15T16:44:54.130Z"
    },
    {
        "key": "wl_cbv",
        "value": "v2%3Bclient_version%3A2819%3Btimestamp%3A1747324933",
        "domain": "facebook.com",
        "path": "/",
        "hostOnly": false,
        "creation": "2025-05-15T16:44:54.130Z",
        "lastAccessed": "2025-05-15T16:44:54.130Z"
    },
    {
        "key": "fbl_st",
        "value": "100632387%3BT%3A29122082",
        "domain": "facebook.com",
        "path": "/",
        "hostOnly": false,
        "creation": "2025-05-15T16:44:54.130Z",
        "lastAccessed": "2025-05-15T16:44:54.130Z"
    },
    {
        "key": "vpd",
        "value": "v1%3B764x393x2.75",
        "domain": "facebook.com",
        "path": "/",
        "hostOnly": false,
        "creation": "2025-05-15T16:44:54.130Z",
        "lastAccessed": "2025-05-15T16:44:54.130Z"
    }
]
